gsheetdb/__init__.py
gsheetdb-1.2.4.dist-info/METADATA
gsheetdb-1.2.4.dist-info/WHEEL
gsheetdb-1.2.4.dist-info/top_level.txt
gsheetdb-1.2.4.dist-info/RECORD
