Metadata-Version: 2.4
Name: gsheetdb
Version: 1.2.4
Summary: A simple way to use Google Sheet as your Data Base.
Author-email: Lucas Prett Campagna <lucasprett129@gmail.com>
Project-URL: Homepage, https://github.com/yourusername/gsheetdb
Project-URL: Bug Tracker, https://github.com/yourusername/gsheetdb/issues
Classifier: Programming Language :: Python :: 3
Classifier: License :: OSI Approved :: MIT License
Requires-Python: >=3.6
Requires-Dist: requests
